[{"strike":31240.0,"call_prem_buy":0.0,"call_prem_sell":1470.0,"put_prem_buy":0.0,"put_prem_sell":0.0,"gamma_flow":-0.4268193473,"charm_flow":78012.3591816441,"delta_flow":-0.9144700106,"net_call_prem":-1470.0,"net_put_prem":0.0},{"strike":31230.0,"call_prem_buy":0.0,"call_prem_sell":360.0,"put_prem_buy":0.0,"put_prem_sell":0.0,"gamma_flow":-0.2610830876,"charm_flow":47015.0838873303,"delta_flow":-0.5539910484,"net_call_prem":-360.0,"net_put_prem":0.0},{"strike":31220.0,"call_prem_buy":0.0,"call_prem_sell":360.0,"put_prem_buy":0.0,"put_prem_sell":0.0,"gamma_flow":-0.1775030782,"charm_flow":31485.0505705337,"delta_flow":-0.3729862607,"net_call_prem":-360.0,"net_put_prem":0.0},{"strike":31210.0,"call_prem_buy":0.0,"call_prem_sell":960.0,"put_prem_buy":0.0,"put_prem_sell":0.0,"gamma_flow":-0.3621537782,"charm_flow":63260.0253709091,"delta_flow":-0.7535407225,"net_call_prem":-960.0,"net_put_prem":0.0},{"strike":31200.0,"call_prem_buy":0.0,"call_prem_sell":23668.0,"put_prem_buy":0.0,"put_prem_sell":0.0,"gamma_flow":-5.9746603504,"charm_flow":1027500.3809646936,"delta_flow":-12.3088373445,"net_call_prem":-23668.0,"net_put_prem":0.0},{"strike":31190.0,"call_prem_buy":0.0,"call_prem_sell":3220.0,"put_prem_buy":0.0,"put_prem_sell":0.0,"gamma_flow":-0.7227630205,"charm_flow":122345.2619316778,"delta_flow":-1.4733825147,"net_call_prem":-3220.0,"net_put_prem":0.0},{"strike":31180.0,"call_prem_buy":0.0,"call_prem_sell":2635.0,"put_prem_buy":0.0,"put_prem_sell":0.0,"gamma_flow":-0.5455243369,"charm_flow":90869.2027010628,"delta_flow":-1.1008959108,"net_call_prem":-2635.0,"net_put_prem":0.0},{"strike":31170.0,"call_prem_buy":0.0,"call_prem_sell":2170.0,"put_prem_buy":0.0,"put_prem_sell":0.0,"gamma_flow":-0.4679172174,"charm_flow":76687.2014893598,"delta_flow":-0.9588455931,"net_call_prem":-2170.0,"net_put_prem":0.0},{"strike":31160.0,"call_prem_buy":0.0,"call_prem_sell":4760.0,"put_prem_buy":0.0,"put_prem_sell":0.0,"gamma_flow":-0.9375571658,"charm_flow":151101.911851348,"delta_flow":-1.8526530161,"net_call_prem":-4760.0,"net_put_prem":0.0},{"strike":31150.0,"call_prem_buy":0.0,"call_prem_sell":4900.0,"put_prem_buy":0.0,"put_prem_sell":0.0,"gamma_flow":-0.9580420231,"charm_flow":151812.3262060075,"delta_flow":-1.8725156712,"net_call_prem":-4900.0,"net_put_prem":0.0},{"strike":31140.0,"call_prem_buy":0.0,"call_prem_sell":24000.0,"put_prem_buy":0.0,"put_prem_sell":0.0,"gamma_flow":-5.3792770489,"charm_flow":837996.6877712965,"delta_flow":-10.7625487283,"net_call_prem":-24000.0,"net_put_prem":0.0},{"strike":31130.0,"call_prem_buy":0.0,"call_prem_sell":8880.0,"put_prem_buy":0.0,"put_prem_sell":0.0,"gamma_flow":-1.7169410902,"charm_flow":262778.0216961108,"delta_flow":-3.2820629629,"net_call_prem":-8880.0,"net_put_prem":0.0},{"strike":31120.0,"call_prem_buy":0.0,"call_prem_sell":9120.0,"put_prem_buy":0.0,"put_prem_sell":0.0,"gamma_flow":-1.3906228597,"charm_flow":209071.3889289095,"delta_flow":-2.628485104,"net_call_prem":-9120.0,"net_put_prem":0.0},{"strike":31110.0,"call_prem_buy":0.0,"call_prem_sell":7140.0,"put_prem_buy":0.0,"put_prem_sell":0.0,"gamma_flow":-1.0487730538,"charm_flow":154837.353701967,"delta_flow":-1.9599016353,"net_call_prem":-7140.0,"net_put_prem":0.0},{"strike":31100.0,"call_prem_buy":0.0,"call_prem_sell":38400.0,"put_prem_buy":0.0,"put_prem_sell":0.0,"gamma_flow":-4.9072058041,"charm_flow":711194.3573339216,"delta_flow":-9.0600140127,"net_call_prem":-38400.0,"net_put_prem":0.0},{"strike":31090.0,"call_prem_buy":0.0,"call_prem_sell":11520.0,"put_prem_buy":0.0,"put_prem_sell":0.0,"gamma_flow":-1.2567905482,"charm_flow":178741.102116675,"delta_flow":-2.2935714724,"net_call_prem":-11520.0,"net_put_prem":0.0},{"strike":31080.0,"call_prem_buy":0.0,"call_prem_sell":7820.0,"put_prem_buy":0.0,"put_prem_sell":0.0,"gamma_flow":-0.9254351467,"charm_flow":129108.3318148905,"delta_flow":-1.6681165169,"net_call_prem":-7820.0,"net_put_prem":0.0},{"strike":31070.0,"call_prem_buy":0.0,"call_prem_sell":12000.0,"put_prem_buy":0.0,"put_prem_sell":0.0,"gamma_flow":-0.9897998305,"charm_flow":135405.5957775683,"delta_flow":-1.7619762528,"net_call_prem":-12000.0,"net_put_prem":0.0},{"strike":31060.0,"call_prem_buy":8800.0,"call_prem_sell":0.0,"put_prem_buy":0.0,"put_prem_sell":0.0,"gamma_flow":0.5272363289,"charm_flow":-70589.5640070771,"delta_flow":0.590552081,"net_call_prem":8800.0,"net_put_prem":0.0},{"strike":31050.0,"call_prem_buy":0.0,"call_prem_sell":65250.0,"put_prem_buy":0.0,"put_prem_sell":0.0,"gamma_flow":-6.2922888222,"charm_flow":826675.9266027622,"delta_flow":-10.9200759313,"net_call_prem":-65250.0,"net_put_prem":0.0},{"strike":31040.0,"call_prem_buy":0.0,"call_prem_sell":8190.0,"put_prem_buy":0.0,"put_prem_sell":0.0,"gamma_flow":-0.5791440672,"charm_flow":74516.9516255523,"delta_flow":-0.9921872971,"net_call_prem":-8190.0,"net_put_prem":0.0},{"strike":31030.0,"call_prem_buy":1980.0,"call_prem_sell":1980.0,"put_prem_buy":0.0,"put_prem_sell":0.0,"gamma_flow":0.0,"charm_flow":0.0,"delta_flow":0.0,"net_call_prem":0.0,"net_put_prem":0.0},{"strike":31020.0,"call_prem_buy":24414.0,"call_prem_sell":0.0,"put_prem_buy":0.0,"put_prem_sell":0.0,"gamma_flow":1.3603225803,"charm_flow":-167452.6301556653,"delta_flow":1.6199310853,"net_call_prem":24414.0,"net_put_prem":0.0},{"strike":31010.0,"call_prem_buy":7200.0,"call_prem_sell":7200.0,"put_prem_buy":0.0,"put_prem_sell":0.0,"gamma_flow":0.0,"charm_flow":0.0,"delta_flow":0.0,"net_call_prem":0.0,"net_put_prem":0.0},{"strike":31000.0,"call_prem_buy":140250.0,"call_prem_sell":0.0,"put_prem_buy":0.0,"put_prem_sell":0.0,"gamma_flow":7.1973853753,"charm_flow":-847046.2268361305,"delta_flow":8.580487926,"net_call_prem":140250.0,"net_put_prem":0.0},{"strike":30990.0,"call_prem_buy":6450.0,"call_prem_sell":6450.0,"put_prem_buy":0.0,"put_prem_sell":0.0,"gamma_flow":0.0,"charm_flow":0.0,"delta_flow":0.0,"net_call_prem":0.0,"net_put_prem":0.0},{"strike":30980.0,"call_prem_buy":8487.0,"call_prem_sell":8487.0,"put_prem_buy":0.0,"put_prem_sell":0.0,"gamma_flow":0.0,"charm_flow":0.0,"delta_flow":0.0,"net_call_prem":0.0,"net_put_prem":0.0},{"strike":30970.0,"call_prem_buy":43680.0,"call_prem_sell":0.0,"put_prem_buy":0.0,"put_prem_sell":0.0,"gamma_flow":1.7397847119,"charm_flow":-190794.8075402725,"delta_flow":2.7034714533,"net_call_prem":43680.0,"net_put_prem":0.0},{"strike":30960.0,"call_prem_buy":15633.0,"call_prem_sell":15633.0,"put_prem_buy":0.0,"put_prem_sell":0.0,"gamma_flow":0.0,"charm_flow":0.0,"delta_flow":0.0,"net_call_prem":0.0,"net_put_prem":0.0},{"strike":30950.0,"call_prem_buy":0.0,"call_prem_sell":58560.0,"put_prem_buy":0.0,"put_prem_sell":0.0,"gamma_flow":-2.9655496749,"charm_flow":309308.4715330822,"delta_flow":-5.2049227696,"net_call_prem":-58560.0,"net_put_prem":0.0},{"strike":30940.0,"call_prem_buy":8645.0,"call_prem_sell":8645.0,"put_prem_buy":0.0,"put_prem_sell":0.0,"gamma_flow":0.0,"charm_flow":0.0,"delta_flow":0.0,"net_call_prem":0.0,"net_put_prem":0.0},{"strike":30930.0,"call_prem_buy":7225.0,"call_prem_sell":7225.0,"put_prem_buy":0.0,"put_prem_sell":0.0,"gamma_flow":0.0,"charm_flow":0.0,"delta_flow":0.0,"net_call_prem":0.0,"net_put_prem":0.0},{"strike":30920.0,"call_prem_buy":76850.0,"call_prem_sell":0.0,"put_prem_buy":0.0,"put_prem_sell":0.0,"gamma_flow":1.9739143829,"charm_flow":-189774.1574243588,"delta_flow":3.3436081969,"net_call_prem":76850.0,"net_put_prem":0.0},{"strike":30910.0,"call_prem_buy":17550.0,"call_prem_sell":0.0,"put_prem_buy":0.0,"put_prem_sell":0.0,"gamma_flow":0.6386961083,"charm_flow":-59676.3983974506,"delta_flow":1.1043998795,"net_call_prem":17550.0,"net_put_prem":0.0},{"strike":30900.0,"call_prem_buy":0.0,"call_prem_sell":574600.0,"put_prem_buy":0.0,"put_prem_sell":0.0,"gamma_flow":-25.2343569083,"charm_flow":2290416.0372645603,"delta_flow":-48.1106556095,"net_call_prem":-574600.0,"net_put_prem":0.0},{"strike":30890.0,"call_prem_buy":132500.0,"call_prem_sell":0.0,"put_prem_buy":0.0,"put_prem_sell":0.0,"gamma_flow":3.8377942899,"charm_flow":-337795.6358420406,"delta_flow":6.8991092859,"net_call_prem":132500.0,"net_put_prem":0.0},{"strike":30880.0,"call_prem_buy":23397.0,"call_prem_sell":23397.0,"put_prem_buy":0.0,"put_prem_sell":0.0,"gamma_flow":0.0,"charm_flow":0.0,"delta_flow":0.0,"net_call_prem":0.0,"net_put_prem":0.0},{"strike":30870.0,"call_prem_buy":25113.0,"call_prem_sell":25113.0,"put_prem_buy":0.0,"put_prem_sell":0.0,"gamma_flow":0.0,"charm_flow":0.0,"delta_flow":0.0,"net_call_prem":0.0,"net_put_prem":0.0},{"strike":30860.0,"call_prem_buy":90125.0,"call_prem_sell":0.0,"put_prem_buy":0.0,"put_prem_sell":0.0,"gamma_flow":2.9902644868,"charm_flow":-238891.6461845992,"delta_flow":5.7422582907,"net_call_prem":90125.0,"net_put_prem":0.0},{"strike":30850.0,"call_prem_buy":50042.5,"call_prem_sell":50042.5,"put_prem_buy":0.0,"put_prem_sell":0.0,"gamma_flow":0.0,"charm_flow":0.0,"delta_flow":0.0,"net_call_prem":0.0,"net_put_prem":0.0},{"strike":30840.0,"call_prem_buy":45525.0,"call_prem_sell":0.0,"put_prem_buy":0.0,"put_prem_sell":0.0,"gamma_flow":1.3653985294,"charm_flow":-101678.3479299393,"delta_flow":2.7495937985,"net_call_prem":45525.0,"net_put_prem":0.0},{"strike":30830.0,"call_prem_buy":52400.0,"call_prem_sell":0.0,"put_prem_buy":0.0,"put_prem_sell":0.0,"gamma_flow":1.4998385977,"charm_flow":-107621.3466340039,"delta_flow":3.0915401764,"net_call_prem":52400.0,"net_put_prem":0.0},{"strike":30820.0,"call_prem_buy":123200.0,"call_prem_sell":0.0,"put_prem_buy":0.0,"put_prem_sell":0.0,"gamma_flow":2.6977482449,"charm_flow":-186260.1945864239,"delta_flow":5.7039341445,"net_call_prem":123200.0,"net_put_prem":0.0},{"strike":30810.0,"call_prem_buy":102879.0,"call_prem_sell":0.0,"put_prem_buy":76077.0,"put_prem_sell":0.0,"gamma_flow":2.5328844016,"charm_flow":-168076.8573933791,"delta_flow":2.7581972371,"net_call_prem":102879.0,"net_put_prem":76077.0},{"strike":30800.0,"call_prem_buy":257414.0,"call_prem_sell":257414.0,"put_prem_buy":24645.0,"put_prem_sell":0.0,"gamma_flow":0.0908683843,"charm_flow":-5798.8122602235,"delta_flow":-0.7297077417,"net_call_prem":0.0,"net_put_prem":24645.0},{"strike":30790.0,"call_prem_buy":6600.0,"call_prem_sell":0.0,"put_prem_buy":135290.0,"put_prem_sell":0.0,"gamma_flow":0.5634160108,"charm_flow":-34406.2748996603,"delta_flow":-3.3604557817,"net_call_prem":6600.0,"net_put_prem":135290.0},{"strike":30780.0,"call_prem_buy":132300.0,"call_prem_sell":0.0,"put_prem_buy":0.0,"put_prem_sell":0.0,"gamma_flow":2.9748822118,"charm_flow":-173073.0184995014,"delta_flow":6.8936982661,"net_call_prem":132300.0,"net_put_prem":0.0},{"strike":30770.0,"call_prem_buy":67046.0,"call_prem_sell":0.0,"put_prem_buy":93068.0,"put_prem_sell":0.0,"gamma_flow":1.8976995291,"charm_flow":-105324.5327925941,"delta_flow":0.8011344108,"net_call_prem":67046.0,"net_put_prem":93068.0},{"strike":30760.0,"call_prem_buy":36600.0,"call_prem_sell":0.0,"put_prem_buy":124975.0,"put_prem_sell":0.0,"gamma_flow":1.1376513119,"charm_flow":-60107.6220549914,"delta_flow":-1.8258699947,"net_call_prem":36600.0,"net_put_prem":124975.0},{"strike":30750.0,"call_prem_buy":400710.0,"call_prem_sell":0.0,"put_prem_buy":0.0,"put_prem_sell":34518.0,"gamma_flow":6.3226363075,"charm_flow":-316247.3947764363,"delta_flow":16.6777059509,"net_call_prem":400710.0,"net_put_prem":-34518.0},{"strike":30740.0,"call_prem_buy":47160.0,"call_prem_sell":0.0,"put_prem_buy":0.0,"put_prem_sell":0.0,"gamma_flow":0.910193518,"charm_flow":-43059.870434067,"delta_flow":2.3544667399,"net_call_prem":47160.0,"net_put_prem":0.0},{"strike":30730.0,"call_prem_buy":278752.0,"call_prem_sell":0.0,"put_prem_buy":0.0,"put_prem_sell":0.0,"gamma_flow":3.7264649057,"charm_flow":-166118.1311786902,"delta_flow":9.7352220278,"net_call_prem":278752.0,"net_put_prem":0.0},{"strike":30720.0,"call_prem_buy":50526.0,"call_prem_sell":0.0,"put_prem_buy":378000.0,"put_prem_sell":0.0,"gamma_flow":2.9349954776,"charm_flow":-123270.0070203525,"delta_flow":-11.460659773,"net_call_prem":50526.0,"net_put_prem":378000.0},{"strike":30710.0,"call_prem_buy":46075.0,"call_prem_sell":0.0,"put_prem_buy":209388.0,"put_prem_sell":0.0,"gamma_flow":1.788570476,"charm_flow":-70264.7045522369,"delta_flow":-6.0077998633,"net_call_prem":46075.0,"net_put_prem":209388.0},{"strike":30700.0,"call_prem_buy":630120.0,"call_prem_sell":0.0,"put_prem_buy":84675.0,"put_prem_sell":0.0,"gamma_flow":11.154026307,"charm_flow":-406337.0061737638,"delta_flow":27.4088460743,"net_call_prem":630120.0,"net_put_prem":84675.0},{"strike":30690.0,"call_prem_buy":37676.0,"call_prem_sell":0.0,"put_prem_buy":305850.0,"put_prem_sell":0.0,"gamma_flow":2.0284955014,"charm_flow":-68637.6176570096,"delta_flow":-7.8842530163,"net_call_prem":37676.0,"net_put_prem":305850.0},{"strike":30680.0,"call_prem_buy":238500.0,"call_prem_sell":0.0,"put_prem_buy":119160.0,"put_prem_sell":0.0,"gamma_flow":4.3914844054,"charm_flow":-136009.6645287268,"delta_flow":7.2511841941,"net_call_prem":238500.0,"net_put_prem":119160.0},{"strike":30670.0,"call_prem_buy":648962.0,"call_prem_sell":0.0,"put_prem_buy":0.0,"put_prem_sell":1760000.0,"gamma_flow":-0.9725741765,"charm_flow":29129.0789523105,"delta_flow":78.2978353761,"net_call_prem":648962.0,"net_put_prem":-1760000.0},{"strike":30660.0,"call_prem_buy":143837.0,"call_prem_sell":0.0,"put_prem_buy":753200.0,"put_prem_sell":0.0,"gamma_flow":6.2774438909,"charm_flow":-160960.6452643064,"delta_flow":-16.8526084693,"net_call_prem":143837.0,"net_put_prem":753200.0},{"strike":30650.0,"call_prem_buy":254800.0,"call_prem_sell":0.0,"put_prem_buy":1170000.0,"put_prem_sell":0.0,"gamma_flow":10.0794257352,"charm_flow":-230928.0695923464,"delta_flow":-27.0363744751,"net_call_prem":254800.0,"net_put_prem":1170000.0},{"strike":30640.0,"call_prem_buy":176890.0,"call_prem_sell":0.0,"put_prem_buy":563310.0,"put_prem_sell":0.0,"gamma_flow":5.852677612,"charm_flow":-118033.6180924768,"delta_flow":-10.7726648851,"net_call_prem":176890.0,"net_put_prem":563310.0},{"strike":30630.0,"call_prem_buy":414000.0,"call_prem_sell":0.0,"put_prem_buy":513670.0,"put_prem_sell":0.0,"gamma_flow":8.3158518508,"charm_flow":-144671.2482208211,"delta_flow":-0.0205324448,"net_call_prem":414000.0,"net_put_prem":513670.0},{"strike":30620.0,"call_prem_buy":117495.5,"call_prem_sell":117495.5,"put_prem_buy":250224.0,"put_prem_sell":0.0,"gamma_flow":1.6928905208,"charm_flow":-25022.7478220492,"delta_flow":-8.7392415941,"net_call_prem":0.0,"net_put_prem":250224.0},{"strike":30610.0,"call_prem_buy":701046.0,"call_prem_sell":0.0,"put_prem_buy":733698.0,"put_prem_sell":0.0,"gamma_flow":12.2036005637,"charm_flow":-145771.8811431827,"delta_flow":-5.6457237487,"net_call_prem":701046.0,"net_put_prem":733698.0},{"strike":30600.0,"call_prem_buy":600875.0,"call_prem_sell":600875.0,"put_prem_buy":382800.0,"put_prem_sell":382800.0,"gamma_flow":0.0,"charm_flow":0.0,"delta_flow":0.0,"net_call_prem":0.0,"net_put_prem":0.0},{"strike":30590.0,"call_prem_buy":478702.4999999999,"call_prem_sell":478702.4999999999,"put_prem_buy":302379.0,"put_prem_sell":0.0,"gamma_flow":2.2269539483,"charm_flow":-14652.7038011158,"delta_flow":-10.8004807766,"net_call_prem":0.0,"net_put_prem":302379.0},{"strike":30580.0,"call_prem_buy":682074.0,"call_prem_sell":0.0,"put_prem_buy":264547.5,"put_prem_sell":264547.5,"gamma_flow":6.853647688,"charm_flow":-25028.8514091069,"delta_flow":26.7129731639,"net_call_prem":682074.0,"net_put_prem":0.0},{"strike":30570.0,"call_prem_buy":794580.0,"call_prem_sell":0.0,"put_prem_buy":602448.0,"put_prem_sell":0.0,"gamma_flow":11.6041271454,"charm_flow":-11534.6904245522,"delta_flow":8.208384892,"net_call_prem":794580.0,"net_put_prem":602448.0},{"strike":30560.0,"call_prem_buy":1009470.0000000001,"call_prem_sell":0.0,"put_prem_buy":888875.0,"put_prem_sell":0.0,"gamma_flow":15.4947830648,"charm_flow":26835.2440130024,"delta_flow":4.5048405896,"net_call_prem":1009470.0000000001,"net_put_prem":888875.0},{"strike":30550.0,"call_prem_buy":945915.0,"call_prem_sell":0.0,"put_prem_buy":298060.0,"put_prem_sell":0.0,"gamma_flow":10.0873600244,"charm_flow":45403.2160271567,"delta_flow":17.1333592752,"net_call_prem":945915.0,"net_put_prem":298060.0},{"strike":30540.0,"call_prem_buy":246400.0,"call_prem_sell":0.0,"put_prem_buy":192030.0,"put_prem_sell":0.0,"gamma_flow":3.3288113678,"charm_flow":23995.9748110844,"delta_flow":0.7089346252,"net_call_prem":246400.0,"net_put_prem":192030.0},{"strike":30530.0,"call_prem_buy":1104000.0,"call_prem_sell":0.0,"put_prem_buy":152165.0,"put_prem_sell":0.0,"gamma_flow":9.9359666356,"charm_flow":99478.971970322,"delta_flow":32.5980838856,"net_call_prem":1104000.0,"net_put_prem":152165.0},{"strike":30520.0,"call_prem_buy":0.0,"call_prem_sell":943295.9999999999,"put_prem_buy":57000.0,"put_prem_sell":0.0,"gamma_flow":-7.778866893,"charm_flow":-99533.0907677664,"delta_flow":-41.3893680606,"net_call_prem":-943295.9999999999,"net_put_prem":57000.0},{"strike":30510.0,"call_prem_buy":719724.0000000001,"call_prem_sell":0.0,"put_prem_buy":18052.5,"put_prem_sell":18052.5,"gamma_flow":4.5707438366,"charm_flow":70977.8336383392,"delta_flow":21.5556907912,"net_call_prem":719724.0000000001,"net_put_prem":0.0},{"strike":30500.0,"call_prem_buy":1543860.0,"call_prem_sell":0.0,"put_prem_buy":0.0,"put_prem_sell":940410.0,"gamma_flow":1.6206785339,"charm_flow":31293.1525516544,"delta_flow":82.2293450076,"net_call_prem":1543860.0,"net_put_prem":-940410.0},{"strike":30490.0,"call_prem_buy":1431815.0,"call_prem_sell":0.0,"put_prem_buy":114686.0,"put_prem_sell":0.0,"gamma_flow":10.3992743139,"charm_flow":218259.8451597251,"delta_flow":42.1607550583,"net_call_prem":1431815.0,"net_put_prem":114686.0},{"strike":30480.0,"call_prem_buy":1175330.0,"call_prem_sell":0.0,"put_prem_buy":0.0,"put_prem_sell":189465.0,"gamma_flow":6.1104702308,"charm_flow":145558.409174851,"delta_flow":47.0505622439,"net_call_prem":1175330.0,"net_put_prem":-189465.0},{"strike":30470.0,"call_prem_buy":195220.0,"call_prem_sell":0.0,"put_prem_buy":60498.0,"put_prem_sell":60498.0,"gamma_flow":1.1943007337,"charm_flow":31663.7048485411,"delta_flow":6.3145284687,"net_call_prem":195220.0,"net_put_prem":0.0},{"strike":30460.0,"call_prem_buy":1029800.0,"call_prem_sell":0.0,"put_prem_buy":53344.5,"put_prem_sell":53344.5,"gamma_flow":5.9051462695,"charm_flow":172786.4036883092,"delta_flow":32.1685896102,"net_call_prem":1029800.0,"net_put_prem":0.0},{"strike":30450.0,"call_prem_buy":1192249.0,"call_prem_sell":0.0,"put_prem_buy":261660.0,"put_prem_sell":261660.0,"gamma_flow":5.4893444402,"charm_flow":175715.5051830932,"delta_flow":30.800709381,"net_call_prem":1192249.0,"net_put_prem":0.0},{"strike":30440.0,"call_prem_buy":147690.0,"call_prem_sell":0.0,"put_prem_buy":0.0,"put_prem_sell":105490.0,"gamma_flow":-0.3884285176,"charm_flow":-13279.0897132002,"delta_flow":7.9576663548,"net_call_prem":147690.0,"net_put_prem":-105490.0},{"strike":30430.0,"call_prem_buy":558048.0,"call_prem_sell":0.0,"put_prem_buy":40095.0,"put_prem_sell":40095.0,"gamma_flow":2.6987366527,"charm_flow":101199.5449429338,"delta_flow":16.2325284363,"net_call_prem":558048.0,"net_put_prem":0.0},{"strike":30420.0,"call_prem_buy":27517.0,"call_prem_sell":0.0,"put_prem_buy":0.0,"put_prem_sell":53160.0,"gamma_flow":-0.4681131487,"charm_flow":-18731.8500487365,"delta_flow":2.7246662361,"net_call_prem":27517.0,"net_put_prem":-53160.0},{"strike":30410.0,"call_prem_buy":28237.0,"call_prem_sell":0.0,"put_prem_buy":38450.0,"put_prem_sell":0.0,"gamma_flow":0.5755898298,"charm_flow":24647.9604976623,"delta_flow":-0.9728349249,"net_call_prem":28237.0,"net_put_prem":38450.0},{"strike":30400.0,"call_prem_buy":3889535.0,"call_prem_sell":3889535.0,"put_prem_buy":303200.0,"put_prem_sell":0.0,"gamma_flow":3.7199224458,"charm_flow":169426.7068873153,"delta_flow":-12.9293636952,"net_call_prem":0.0,"net_put_prem":303200.0},{"strike":30390.0,"call_prem_buy":303839.9999999999,"call_prem_sell":0.0,"put_prem_buy":176700.0,"put_prem_sell":0.0,"gamma_flow":3.53961006,"charm_flow":171195.0318715866,"delta_flow":0.740786829,"net_call_prem":303839.9999999999,"net_put_prem":176700.0},{"strike":30380.0,"call_prem_buy":144150.0,"call_prem_sell":0.0,"put_prem_buy":0.0,"put_prem_sell":610740.0,"gamma_flow":-6.506226466,"charm_flow":-331977.8996472381,"delta_flow":27.550242885,"net_call_prem":144150.0,"net_put_prem":-610740.0},{"strike":30370.0,"call_prem_buy":62000.0,"call_prem_sell":0.0,"put_prem_buy":34090.0,"put_prem_sell":0.0,"gamma_flow":0.6476087536,"charm_flow":34887.2129436376,"delta_flow":-0.0032069174,"net_call_prem":62000.0,"net_put_prem":34090.0},{"strike":30360.0,"call_prem_buy":0.0,"call_prem_sell":0.0,"put_prem_buy":0.0,"put_prem_sell":65115.0,"gamma_flow":-0.7887820486,"charm_flow":-44610.8325904074,"delta_flow":2.5954421116,"net_call_prem":0.0,"net_put_prem":-65115.0},{"strike":30350.0,"call_prem_buy":357000.0,"call_prem_sell":0.0,"put_prem_buy":182590.0,"put_prem_sell":0.0,"gamma_flow":4.4413065163,"charm_flow":263682.4100066415,"delta_flow":-1.5200154922,"net_call_prem":357000.0,"net_put_prem":182590.0},{"strike":30340.0,"call_prem_buy":359820.0,"call_prem_sell":0.0,"put_prem_buy":77560.0,"put_prem_sell":0.0,"gamma_flow":2.1308589428,"charm_flow":132462.0837289768,"delta_flow":3.87444394,"net_call_prem":359820.0,"net_put_prem":77560.0},{"strike":30330.0,"call_prem_buy":0.0,"call_prem_sell":132325.0,"put_prem_buy":27900.0,"put_prem_sell":27900.0,"gamma_flow":-0.4633146509,"charm_flow":-30141.32851303,"delta_flow":-3.9008657315,"net_call_prem":-132325.0,"net_put_prem":0.0},{"strike":30320.0,"call_prem_buy":310900.0,"call_prem_sell":0.0,"put_prem_buy":11388.0,"put_prem_sell":11388.0,"gamma_flow":0.9061043502,"charm_flow":61454.5692273114,"delta_flow":7.9100130588,"net_call_prem":310900.0,"net_put_prem":0.0},{"strike":30310.0,"call_prem_buy":69580.0,"call_prem_sell":0.0,"put_prem_buy":0.0,"put_prem_sell":53325.0,"gamma_flow":-0.5451659781,"charm_flow":-38298.887957789,"delta_flow":3.8463762759,"net_call_prem":69580.0,"net_put_prem":-53325.0},{"strike":30300.0,"call_prem_buy":32655.0,"call_prem_sell":0.0,"put_prem_buy":0.0,"put_prem_sell":214110.0,"gamma_flow":-2.9977295105,"charm_flow":-219132.367362989,"delta_flow":10.1529189762,"net_call_prem":32655.0,"net_put_prem":-214110.0},{"strike":30290.0,"call_prem_buy":204540.0,"call_prem_sell":0.0,"put_prem_buy":0.0,"put_prem_sell":103930.0,"gamma_flow":-1.0504641897,"charm_flow":-79574.1036583833,"delta_flow":8.5466553233,"net_call_prem":204540.0,"net_put_prem":-103930.0},{"strike":30280.0,"call_prem_buy":0.0,"call_prem_sell":512379.9999999999,"put_prem_buy":0.0,"put_prem_sell":94860.0,"gamma_flow":-2.7458002175,"charm_flow":-216248.9791252099,"delta_flow":-10.0399235249,"net_call_prem":-512379.9999999999,"net_put_prem":-94860.0},{"strike":30270.0,"call_prem_buy":68600.0,"call_prem_sell":0.0,"put_prem_buy":0.0,"put_prem_sell":13680.0,"gamma_flow":0.0089808907,"charm_flow":775.7477685848,"delta_flow":2.1203393912,"net_call_prem":68600.0,"net_put_prem":-13680.0},{"strike":30260.0,"call_prem_buy":0.0,"call_prem_sell":0.0,"put_prem_buy":0.0,"put_prem_sell":49740.0,"gamma_flow":-0.7262695565,"charm_flow":-61107.2322847942,"delta_flow":2.1322979005,"net_call_prem":0.0,"net_put_prem":-49740.0},{"strike":30250.0,"call_prem_buy":0.0,"call_prem_sell":0.0,"put_prem_buy":0.0,"put_prem_sell":198000.0,"gamma_flow":-3.1402934222,"charm_flow":-272948.4632429535,"delta_flow":8.9727648132,"net_call_prem":0.0,"net_put_prem":-198000.0},{"strike":30240.0,"call_prem_buy":0.0,"call_prem_sell":0.0,"put_prem_buy":47580.0,"put_prem_sell":0.0,"gamma_flow":0.8368840086,"charm_flow":75049.8462173618,"delta_flow":-2.3779622993,"net_call_prem":0.0,"net_put_prem":47580.0},{"strike":30230.0,"call_prem_buy":0.0,"call_prem_sell":0.0,"put_prem_buy":148395.0,"put_prem_sell":0.0,"gamma_flow":2.6538930002,"charm_flow":245302.2281691629,"delta_flow":-7.5543699873,"net_call_prem":0.0,"net_put_prem":148395.0},{"strike":30220.0,"call_prem_buy":0.0,"call_prem_sell":0.0,"put_prem_buy":0.0,"put_prem_sell":140544.0,"gamma_flow":-2.1288327243,"charm_flow":-202657.6951574178,"delta_flow":6.0025037136,"net_call_prem":0.0,"net_put_prem":-140544.0},{"strike":30210.0,"call_prem_buy":0.0,"call_prem_sell":142020.0,"put_prem_buy":0.0,"put_prem_sell":41980.0,"gamma_flow":-0.9041008503,"charm_flow":-88658.8258662586,"delta_flow":-1.750872533,"net_call_prem":-142020.0,"net_put_prem":-41980.0},{"strike":30200.0,"call_prem_buy":332640.0,"call_prem_sell":0.0,"put_prem_buy":0.0,"put_prem_sell":317997.0,"gamma_flow":-5.1976245477,"charm_flow":-523747.6167032825,"delta_flow":21.8912855025,"net_call_prem":332640.0,"net_put_prem":-317997.0},{"strike":30190.0,"call_prem_buy":0.0,"call_prem_sell":0.0,"put_prem_buy":35893.0,"put_prem_sell":0.0,"gamma_flow":0.6819577969,"charm_flow":70578.4559748702,"delta_flow":-1.8796920074,"net_call_prem":0.0,"net_put_prem":35893.0},{"strike":30180.0,"call_prem_buy":0.0,"call_prem_sell":0.0,"put_prem_buy":0.0,"put_prem_sell":44352.0,"gamma_flow":-0.7262476758,"charm_flow":-77171.8733968262,"delta_flow":1.9879537636,"net_call_prem":0.0,"net_put_prem":-44352.0},{"strike":30170.0,"call_prem_buy":0.0,"call_prem_sell":0.0,"put_prem_buy":0.0,"put_prem_sell":28200.0,"gamma_flow":-0.2953892116,"charm_flow":-32211.5835093663,"delta_flow":0.7881239126,"net_call_prem":0.0,"net_put_prem":-28200.0},{"strike":30160.0,"call_prem_buy":0.0,"call_prem_sell":0.0,"put_prem_buy":0.0,"put_prem_sell":34390.0,"gamma_flow":-0.5762717437,"charm_flow":-64429.7783973049,"delta_flow":1.546751106,"net_call_prem":0.0,"net_put_prem":-34390.0},{"strike":30150.0,"call_prem_buy":0.0,"call_prem_sell":0.0,"put_prem_buy":0.0,"put_prem_sell":176275.0,"gamma_flow":-3.0897172155,"charm_flow":-354036.9525586182,"delta_flow":8.1482669931,"net_call_prem":0.0,"net_put_prem":-176275.0},{"strike":30140.0,"call_prem_buy":0.0,"call_prem_sell":0.0,"put_prem_buy":58305.0,"put_prem_sell":0.0,"gamma_flow":1.2588071058,"charm_flow":147737.5986320356,"delta_flow":-3.2763722186,"net_call_prem":0.0,"net_put_prem":58305.0},{"strike":30130.0,"call_prem_buy":0.0,"call_prem_sell":0.0,"put_prem_buy":0.0,"put_prem_sell":97308.0,"gamma_flow":-1.8124966383,"charm_flow":-217750.3487607151,"delta_flow":4.6723733262,"net_call_prem":0.0,"net_put_prem":-97308.0},{"strike":30120.0,"call_prem_buy":0.0,"call_prem_sell":0.0,"put_prem_buy":0.0,"put_prem_sell":152320.0,"gamma_flow":-1.6614488737,"charm_flow":-204212.0300026627,"delta_flow":4.2530149207,"net_call_prem":0.0,"net_put_prem":-152320.0},{"strike":30110.0,"call_prem_buy":0.0,"call_prem_sell":0.0,"put_prem_buy":0.0,"put_prem_sell":33600.0,"gamma_flow":-0.4048724435,"charm_flow":-50884.4745119797,"delta_flow":1.0358585138,"net_call_prem":0.0,"net_put_prem":-33600.0},{"strike":30100.0,"call_prem_buy":151740.0,"call_prem_sell":0.0,"put_prem_buy":475076.0,"put_prem_sell":0.0,"gamma_flow":9.423995711,"charm_flow":1210176.5567867099,"delta_flow":-21.9134962618,"net_call_prem":151740.0,"net_put_prem":475076.0},{"strike":30090.0,"call_prem_buy":0.0,"call_prem_sell":0.0,"put_prem_buy":0.0,"put_prem_sell":71901.0,"gamma_flow":-1.2999829151,"charm_flow":-170575.7034496392,"delta_flow":3.3412409782,"net_call_prem":0.0,"net_put_prem":-71901.0},{"strike":30080.0,"call_prem_buy":0.0,"call_prem_sell":0.0,"put_prem_buy":86395.0,"put_prem_sell":86395.0,"gamma_flow":0.0,"charm_flow":0.0,"delta_flow":0.0,"net_call_prem":0.0,"net_put_prem":0.0},{"strike":30070.0,"call_prem_buy":0.0,"call_prem_sell":0.0,"put_prem_buy":27060.0,"put_prem_sell":27060.0,"gamma_flow":0.0,"charm_flow":0.0,"delta_flow":0.0,"net_call_prem":0.0,"net_put_prem":0.0},{"strike":30060.0,"call_prem_buy":0.0,"call_prem_sell":0.0,"put_prem_buy":0.0,"put_prem_sell":89300.0,"gamma_flow":-1.6846529547,"charm_flow":-235100.318476851,"delta_flow":4.2233971944,"net_call_prem":0.0,"net_put_prem":-89300.0},{"strike":30050.0,"call_prem_buy":0.0,"call_prem_sell":0.0,"put_prem_buy":0.0,"put_prem_sell":82536.0,"gamma_flow":-1.6274724344,"charm_flow":-231678.9007455129,"delta_flow":3.972830354,"net_call_prem":0.0,"net_put_prem":-82536.0},{"strike":30040.0,"call_prem_buy":0.0,"call_prem_sell":0.0,"put_prem_buy":23650.0,"put_prem_sell":23650.0,"gamma_flow":0.0,"charm_flow":0.0,"delta_flow":0.0,"net_call_prem":0.0,"net_put_prem":0.0},{"strike":30030.0,"call_prem_buy":0.0,"call_prem_sell":0.0,"put_prem_buy":0.0,"put_prem_sell":8332.0,"gamma_flow":-0.1627769224,"charm_flow":-24075.158630954,"delta_flow":0.398449077,"net_call_prem":0.0,"net_put_prem":-8332.0},{"strike":30020.0,"call_prem_buy":0.0,"call_prem_sell":0.0,"put_prem_buy":0.0,"put_prem_sell":26026.0,"gamma_flow":-0.5148494469,"charm_flow":-77578.7708138843,"delta_flow":1.2566333426,"net_call_prem":0.0,"net_put_prem":-26026.0},{"strike":30010.0,"call_prem_buy":0.0,"call_prem_sell":0.0,"put_prem_buy":2617.5,"put_prem_sell":2617.5,"gamma_flow":0.0,"charm_flow":0.0,"delta_flow":0.0,"net_call_prem":0.0,"net_put_prem":0.0},{"strike":30000.0,"call_prem_buy":235396.0,"call_prem_sell":0.0,"put_prem_buy":163350.0,"put_prem_sell":163350.0,"gamma_flow":1.288799699e-19,"charm_flow":0.0,"delta_flow":4.0,"net_call_prem":235396.0,"net_put_prem":0.0},{"strike":29990.0,"call_prem_buy":0.0,"call_prem_sell":0.0,"put_prem_buy":62402.0,"put_prem_sell":0.0,"gamma_flow":1.5068564967,"charm_flow":239607.160686,"delta_flow":-3.7011640037,"net_call_prem":0.0,"net_put_prem":62402.0},{"strike":29980.0,"call_prem_buy":0.0,"call_prem_sell":0.0,"put_prem_buy":0.0,"put_prem_sell":104424.0,"gamma_flow":-2.0247050132,"charm_flow":-327616.373093633,"delta_flow":4.8922996785,"net_call_prem":0.0,"net_put_prem":-104424.0},{"strike":29970.0,"call_prem_buy":0.0,"call_prem_sell":0.0,"put_prem_buy":0.0,"put_prem_sell":12492.0,"gamma_flow":-0.138144825,"charm_flow":-22737.9588484912,"delta_flow":0.332517557,"net_call_prem":0.0,"net_put_prem":-12492.0},{"strike":29960.0,"call_prem_buy":0.0,"call_prem_sell":0.0,"put_prem_buy":8598.0,"put_prem_sell":8598.0,"gamma_flow":0.0,"charm_flow":0.0,"delta_flow":0.0,"net_call_prem":0.0,"net_put_prem":0.0},{"strike":29950.0,"call_prem_buy":0.0,"call_prem_sell":0.0,"put_prem_buy":10117.5,"put_prem_sell":10117.5,"gamma_flow":0.0,"charm_flow":0.0,"delta_flow":0.0,"net_call_prem":0.0,"net_put_prem":0.0},{"strike":29940.0,"call_prem_buy":0.0,"call_prem_sell":0.0,"put_prem_buy":5863.5,"put_prem_sell":5863.5,"gamma_flow":0.0,"charm_flow":0.0,"delta_flow":0.0,"net_call_prem":0.0,"net_put_prem":0.0},{"strike":29930.0,"call_prem_buy":130006.0,"call_prem_sell":0.0,"put_prem_buy":0.0,"put_prem_sell":15025.0,"gamma_flow":-0.1545071681,"charm_flow":-27153.5544409694,"delta_flow":2.3677753701,"net_call_prem":130006.0,"net_put_prem":-15025.0},{"strike":29920.0,"call_prem_buy":0.0,"call_prem_sell":0.0,"put_prem_buy":15062.5,"put_prem_sell":15062.5,"gamma_flow":0.0,"charm_flow":0.0,"delta_flow":0.0,"net_call_prem":0.0,"net_put_prem":0.0},{"strike":29910.0,"call_prem_buy":133806.0,"call_prem_sell":0.0,"put_prem_buy":0.0,"put_prem_sell":12240.0,"gamma_flow":-0.2345295221,"charm_flow":-42524.25456217,"delta_flow":2.5579171522,"net_call_prem":133806.0,"net_put_prem":-12240.0},{"strike":29900.0,"call_prem_buy":138260.0,"call_prem_sell":0.0,"put_prem_buy":173376.0,"put_prem_sell":173376.0,"gamma_flow":0.0,"charm_flow":0.0,"delta_flow":2.0,"net_call_prem":138260.0,"net_put_prem":0.0},{"strike":29890.0,"call_prem_buy":0.0,"call_prem_sell":0.0,"put_prem_buy":122640.0,"put_prem_sell":122640.0,"gamma_flow":0.0,"charm_flow":0.0,"delta_flow":0.0,"net_call_prem":0.0,"net_put_prem":0.0},{"strike":29880.0,"call_prem_buy":0.0,"call_prem_sell":0.0,"put_prem_buy":14168.0,"put_prem_sell":14168.0,"gamma_flow":0.0,"charm_flow":0.0,"delta_flow":0.0,"net_call_prem":0.0,"net_put_prem":0.0},{"strike":29870.0,"call_prem_buy":0.0,"call_prem_sell":0.0,"put_prem_buy":53917.5,"put_prem_sell":53917.5,"gamma_flow":0.0,"charm_flow":0.0,"delta_flow":0.0,"net_call_prem":0.0,"net_put_prem":0.0},{"strike":29860.0,"call_prem_buy":0.0,"call_prem_sell":0.0,"put_prem_buy":0.0,"put_prem_sell":23205.0,"gamma_flow":-0.4285592043,"charm_flow":-83696.2771930568,"delta_flow":0.9944277218,"net_call_prem":0.0,"net_put_prem":-23205.0},{"strike":29850.0,"call_prem_buy":79375.0,"call_prem_sell":0.0,"put_prem_buy":244755.0,"put_prem_sell":244755.0,"gamma_flow":0.0,"charm_flow":0.0,"delta_flow":1.0,"net_call_prem":79375.0,"net_put_prem":0.0},{"strike":29840.0,"call_prem_buy":0.0,"call_prem_sell":0.0,"put_prem_buy":171080.0,"put_prem_sell":171080.0,"gamma_flow":0.0,"charm_flow":0.0,"delta_flow":0.0,"net_call_prem":0.0,"net_put_prem":0.0},{"strike":29830.0,"call_prem_buy":0.0,"call_prem_sell":0.0,"put_prem_buy":15150.0,"put_prem_sell":15150.0,"gamma_flow":0.0,"charm_flow":0.0,"delta_flow":0.0,"net_call_prem":0.0,"net_put_prem":0.0},{"strike":29820.0,"call_prem_buy":0.0,"call_prem_sell":0.0,"put_prem_buy":16335.0,"put_prem_sell":16335.0,"gamma_flow":0.0,"charm_flow":0.0,"delta_flow":0.0,"net_call_prem":0.0,"net_put_prem":0.0},{"strike":29810.0,"call_prem_buy":0.0,"call_prem_sell":0.0,"put_prem_buy":85920.0,"put_prem_sell":85920.0,"gamma_flow":0.0,"charm_flow":0.0,"delta_flow":0.0,"net_call_prem":0.0,"net_put_prem":0.0},{"strike":29800.0,"call_prem_buy":472739.9999999999,"call_prem_sell":0.0,"put_prem_buy":150024.0,"put_prem_sell":150024.0,"gamma_flow":0.0,"charm_flow":0.0,"delta_flow":6.0,"net_call_prem":472739.9999999999,"net_put_prem":0.0},{"strike":29790.0,"call_prem_buy":0.0,"call_prem_sell":72062.0,"put_prem_buy":72775.0,"put_prem_sell":72775.0,"gamma_flow":0.0,"charm_flow":0.0,"delta_flow":-1.0,"net_call_prem":-72062.0,"net_put_prem":0.0},{"strike":29780.0,"call_prem_buy":0.0,"call_prem_sell":0.0,"put_prem_buy":18445.0,"put_prem_sell":18445.0,"gamma_flow":0.0,"charm_flow":0.0,"delta_flow":0.0,"net_call_prem":0.0,"net_put_prem":0.0},{"strike":29770.0,"call_prem_buy":0.0,"call_prem_sell":0.0,"put_prem_buy":15345.0,"put_prem_sell":15345.0,"gamma_flow":0.0,"charm_flow":0.0,"delta_flow":0.0,"net_call_prem":0.0,"net_put_prem":0.0},{"strike":29760.0,"call_prem_buy":0.0,"call_prem_sell":0.0,"put_prem_buy":17845.0,"put_prem_sell":17845.0,"gamma_flow":0.0,"charm_flow":0.0,"delta_flow":0.0,"net_call_prem":0.0,"net_put_prem":0.0},{"strike":29750.0,"call_prem_buy":0.0,"call_prem_sell":0.0,"put_prem_buy":74556.0,"put_prem_sell":74556.0,"gamma_flow":0.0,"charm_flow":0.0,"delta_flow":0.0,"net_call_prem":0.0,"net_put_prem":0.0},{"strike":29740.0,"call_prem_buy":0.0,"call_prem_sell":153684.0,"put_prem_buy":92598.0,"put_prem_sell":0.0,"gamma_flow":2.4323629182,"charm_flow":556462.7911904705,"delta_flow":-8.0884627426,"net_call_prem":-153684.0,"net_put_prem":92598.0}]