[{"strike":746.0,"call_prem_buy":5774.0,"call_prem_sell":0.0,"put_prem_buy":0.0,"put_prem_sell":27800.0,"gamma_flow":433.9315268975,"charm_flow":-7675248.3861674219,"delta_flow":22.6937099747,"net_call_prem":5774.0,"net_put_prem":-27800.0},{"strike":745.0,"call_prem_buy":8167.0,"call_prem_sell":311.0,"put_prem_buy":3482.5,"put_prem_sell":191943.5,"gamma_flow":529.4341060031,"charm_flow":-8862258.2048375476,"delta_flow":91.0426463518,"net_call_prem":7856.0,"net_put_prem":-188461.0},{"strike":744.0,"call_prem_buy":991.0,"call_prem_sell":3703.0,"put_prem_buy":5393.0,"put_prem_sell":260811.0,"gamma_flow":-581.2509427004,"charm_flow":9662543.2773952913,"delta_flow":75.3576453677,"net_call_prem":-2712.0,"net_put_prem":-255418.0},{"strike":743.0,"call_prem_buy":11890.0,"call_prem_sell":898.0,"put_prem_buy":4416.5,"put_prem_sell":273364.5,"gamma_flow":735.890205524,"charm_flow":-12067897.412748998,"delta_flow":130.7924412004,"net_call_prem":10992.0,"net_put_prem":-268948.0},{"strike":742.0,"call_prem_buy":108936050.0,"call_prem_sell":9579.0,"put_prem_buy":70130.0,"put_prem_sell":184786511.0,"gamma_flow":-721.662870623,"charm_flow":11714607.0874601714,"delta_flow":2631.7412054538,"net_call_prem":108926471.0,"net_put_prem":-184716381.0},{"strike":741.0,"call_prem_buy":54323193.0,"call_prem_sell":3784.0,"put_prem_buy":975.0,"put_prem_sell":54175063.0,"gamma_flow":111.9416716781,"charm_flow":-1468294.6780494733,"delta_flow":741.652904109,"net_call_prem":54319409.0,"net_put_prem":-54174088.0},{"strike":740.0,"call_prem_buy":54228294.0,"call_prem_sell":13674.0,"put_prem_buy":285287.5,"put_prem_sell":54948940.5,"gamma_flow":2334.1734368881,"charm_flow":-35123212.7451215982,"delta_flow":1112.4924807867,"net_call_prem":54214620.0,"net_put_prem":-54663653.0},{"strike":739.0,"call_prem_buy":54040121.0,"call_prem_sell":16378.0,"put_prem_buy":360445.5,"put_prem_sell":54126793.5,"gamma_flow":-322.416842125,"charm_flow":3429842.0587287205,"delta_flow":663.4258173392,"net_call_prem":54023743.0,"net_put_prem":-53766348.0},{"strike":738.0,"call_prem_buy":13114.0,"call_prem_sell":19336.0,"put_prem_buy":1227651.0,"put_prem_sell":475622.0,"gamma_flow":55.3688042437,"charm_flow":-1400133.2366966661,"delta_flow":-262.8186418183,"net_call_prem":-6222.0,"net_put_prem":752029.0},{"strike":737.0,"call_prem_buy":28334.0,"call_prem_sell":26281.0,"put_prem_buy":835955.5,"put_prem_sell":1880262.5,"gamma_flow":1.6831435108,"charm_flow":1257749.2490378392,"delta_flow":469.7884876244,"net_call_prem":2053.0,"net_put_prem":-1044307.0},{"strike":736.0,"call_prem_buy":24179.0,"call_prem_sell":24611.0,"put_prem_buy":500134.0,"put_prem_sell":1526766.0,"gamma_flow":-475.0292976338,"charm_flow":6641799.8271236941,"delta_flow":433.8634420873,"net_call_prem":-432.0,"net_put_prem":-1026632.0},{"strike":735.0,"call_prem_buy":83585.0,"call_prem_sell":47205.0,"put_prem_buy":1265992.0,"put_prem_sell":2311294.0,"gamma_flow":1569.147354424,"charm_flow":-22096265.9346620366,"delta_flow":613.9214795169,"net_call_prem":36380.0,"net_put_prem":-1045302.0},{"strike":734.0,"call_prem_buy":143618.0,"call_prem_sell":72166.0,"put_prem_buy":224338.5,"put_prem_sell":675204.5,"gamma_flow":4001.48525987,"charm_flow":-36396388.3160468712,"delta_flow":414.6754141595,"net_call_prem":71452.0,"net_put_prem":-450866.0},{"strike":733.0,"call_prem_buy":74767.0,"call_prem_sell":39692.0,"put_prem_buy":332901.0,"put_prem_sell":1073931.0,"gamma_flow":1757.6556636679,"charm_flow":-17713325.163078066,"delta_flow":526.5859794415,"net_call_prem":35075.0,"net_put_prem":-741030.0},{"strike":732.0,"call_prem_buy":136089.0,"call_prem_sell":117457.0,"put_prem_buy":589501.0,"put_prem_sell":1250669.0,"gamma_flow":854.629568654,"charm_flow":-6553944.8910897551,"delta_flow":490.1305098163,"net_call_prem":18632.0,"net_put_prem":-661168.0},{"strike":731.0,"call_prem_buy":236402.5,"call_prem_sell":242658.5,"put_prem_buy":155381.0,"put_prem_sell":387396.0,"gamma_flow":-2875.6259593584,"charm_flow":11878969.4025654458,"delta_flow":60.0086653476,"net_call_prem":-6256.0,"net_put_prem":-232015.0},{"strike":730.0,"call_prem_buy":1405118.0,"call_prem_sell":1716078.0,"put_prem_buy":1432786.5,"put_prem_sell":2427958.5,"gamma_flow":-22607.2637017907,"charm_flow":117268917.2413425744,"delta_flow":-490.5949027134,"net_call_prem":-310960.0,"net_put_prem":-995172.0},{"strike":729.0,"call_prem_buy":741426.0,"call_prem_sell":437119.0,"put_prem_buy":2070433.5,"put_prem_sell":194747.5,"gamma_flow":17047.5614821381,"charm_flow":-108445246.0519548953,"delta_flow":-664.7160209748,"net_call_prem":304307.0,"net_put_prem":1875686.0},{"strike":728.0,"call_prem_buy":952785.5,"call_prem_sell":1333094.5,"put_prem_buy":454858.5,"put_prem_sell":1041558.5,"gamma_flow":-16822.1666670663,"charm_flow":121524019.8225915283,"delta_flow":-387.9314900274,"net_call_prem":-380309.0,"net_put_prem":-586700.0},{"strike":727.0,"call_prem_buy":1817010.0,"call_prem_sell":1930594.0,"put_prem_buy":507041.5,"put_prem_sell":583736.5,"gamma_flow":-5726.6590585815,"charm_flow":-35127134.028734237,"delta_flow":-578.6912765421,"net_call_prem":-113584.0,"net_put_prem":-76695.0},{"strike":726.0,"call_prem_buy":2484712.5,"call_prem_sell":2226011.5,"put_prem_buy":615929.0,"put_prem_sell":423551.0,"gamma_flow":10979.2058078811,"charm_flow":-92857640.2746393532,"delta_flow":56.6931513689,"net_call_prem":258701.0,"net_put_prem":192378.0},{"strike":725.0,"call_prem_buy":5805164.0,"call_prem_sell":5690286.0,"put_prem_buy":2095745.5,"put_prem_sell":2188021.5,"gamma_flow":-10301.3382087303,"charm_flow":29883512.2161542773,"delta_flow":-543.5725319416,"net_call_prem":114878.0,"net_put_prem":-92276.0},{"strike":724.0,"call_prem_buy":4607151.0,"call_prem_sell":4897531.0,"put_prem_buy":1985161.0,"put_prem_sell":1971862.0,"gamma_flow":6853.1313696984,"charm_flow":-19258236.0119277984,"delta_flow":-1266.3550998201,"net_call_prem":-290380.0,"net_put_prem":13299.0},{"strike":723.0,"call_prem_buy":7567726.5,"call_prem_sell":10033078.5,"put_prem_buy":3389739.0,"put_prem_sell":3589492.0,"gamma_flow":-64098.7663153119,"charm_flow":55904467.4142894819,"delta_flow":-4718.1346476345,"net_call_prem":-2465352.0,"net_put_prem":-199753.0},{"strike":722.0,"call_prem_buy":10168717.5,"call_prem_sell":9416998.5,"put_prem_buy":8264159.0,"put_prem_sell":8133029.0,"gamma_flow":4302.9828615283,"charm_flow":36458215.459971875,"delta_flow":-7.70788718,"net_call_prem":751719.0,"net_put_prem":131130.0},{"strike":721.0,"call_prem_buy":9812727.5,"call_prem_sell":6917410.5,"put_prem_buy":10151558.0,"put_prem_sell":7228373.0,"gamma_flow":98235.2506386442,"charm_flow":-43936893.1901090145,"delta_flow":-561.933525873,"net_call_prem":2895317.0,"net_put_prem":2923185.0},{"strike":720.0,"call_prem_buy":16514870.0,"call_prem_sell":11671582.0,"put_prem_buy":17804282.5,"put_prem_sell":8195004.5,"gamma_flow":289969.934280977,"charm_flow":20293511.7400307134,"delta_flow":-9509.398674376,"net_call_prem":4843288.0,"net_put_prem":9609278.0},{"strike":719.0,"call_prem_buy":10603246.0,"call_prem_sell":4190434.0,"put_prem_buy":9759367.0,"put_prem_sell":5760379.0,"gamma_flow":174546.8691465913,"charm_flow":31573084.5255703703,"delta_flow":1565.2579817598,"net_call_prem":6412812.0,"net_put_prem":3998988.0},{"strike":718.0,"call_prem_buy":10804501.0,"call_prem_sell":5976913.0,"put_prem_buy":5878987.5,"put_prem_sell":7494158.5,"gamma_flow":49136.5588419001,"charm_flow":128545862.18751885,"delta_flow":10282.9184395064,"net_call_prem":4827588.0,"net_put_prem":-1615171.0},{"strike":717.0,"call_prem_buy":9739202.0,"call_prem_sell":3725201.0,"put_prem_buy":5245241.5,"put_prem_sell":4799936.5,"gamma_flow":65605.6076214395,"charm_flow":21558634.6771309152,"delta_flow":6592.7678222215,"net_call_prem":6014001.0,"net_put_prem":445305.0},{"strike":716.0,"call_prem_buy":6371578.5,"call_prem_sell":4332299.5,"put_prem_buy":4435156.5,"put_prem_sell":4021988.5,"gamma_flow":13014.7237807999,"charm_flow":-38095507.9132697508,"delta_flow":1551.1963413231,"net_call_prem":2039279.0,"net_put_prem":413168.0},{"strike":715.0,"call_prem_buy":3591834.5,"call_prem_sell":3643477.5,"put_prem_buy":7411788.0,"put_prem_sell":7801726.0,"gamma_flow":15874.5898547007,"charm_flow":124495605.754793793,"delta_flow":-538.3880870051,"net_call_prem":-51643.0,"net_put_prem":-389938.0},{"strike":714.0,"call_prem_buy":871830.5,"call_prem_sell":1905262.5,"put_prem_buy":3439514.0,"put_prem_sell":2459147.0,"gamma_flow":22038.5796211287,"charm_flow":108639418.9296281785,"delta_flow":-3197.7774124948,"net_call_prem":-1033432.0,"net_put_prem":980367.0},{"strike":713.0,"call_prem_buy":592858.0,"call_prem_sell":772852.0,"put_prem_buy":2329474.5,"put_prem_sell":2872656.5,"gamma_flow":20.7977007422,"charm_flow":21125496.0832985416,"delta_flow":40.5723869793,"net_call_prem":-179994.0,"net_put_prem":-543182.0},{"strike":712.0,"call_prem_buy":515485.0,"call_prem_sell":202649.0,"put_prem_buy":1841440.5,"put_prem_sell":1402687.5,"gamma_flow":13831.641042437,"charm_flow":71282228.9628030658,"delta_flow":-612.9738713053,"net_call_prem":312836.0,"net_put_prem":438753.0},{"strike":711.0,"call_prem_buy":208033.5,"call_prem_sell":272844.5,"put_prem_buy":1137294.0,"put_prem_sell":693473.0,"gamma_flow":4644.3600772804,"charm_flow":10782058.2034230679,"delta_flow":-653.050657884,"net_call_prem":-64811.0,"net_put_prem":443821.0},{"strike":710.0,"call_prem_buy":1050284.0,"call_prem_sell":848834.0,"put_prem_buy":3814849.0,"put_prem_sell":1857164.0,"gamma_flow":39159.2748736143,"charm_flow":210320008.0088842511,"delta_flow":-2981.3041545938,"net_call_prem":201450.0,"net_put_prem":1957685.0},{"strike":709.0,"call_prem_buy":213481.0,"call_prem_sell":182230.0,"put_prem_buy":1096876.0,"put_prem_sell":1015571.0,"gamma_flow":9585.8334514396,"charm_flow":89658001.5908118635,"delta_flow":-436.9355799919,"net_call_prem":31251.0,"net_put_prem":81305.0},{"strike":708.0,"call_prem_buy":58673.0,"call_prem_sell":347628.0,"put_prem_buy":529151.0,"put_prem_sell":639486.0,"gamma_flow":-2318.2902412438,"charm_flow":-22751089.0126147419,"delta_flow":-109.0896989196,"net_call_prem":-288955.0,"net_put_prem":-110335.0},{"strike":707.0,"call_prem_buy":26275.0,"call_prem_sell":59843.0,"put_prem_buy":621619.0,"put_prem_sell":498531.0,"gamma_flow":3964.4004944557,"charm_flow":36199106.5212849155,"delta_flow":-296.6263198291,"net_call_prem":-33568.0,"net_put_prem":123088.0},{"strike":706.0,"call_prem_buy":24913.5,"call_prem_sell":151819.5,"put_prem_buy":177625.0,"put_prem_sell":389771.0,"gamma_flow":-5377.459559931,"charm_flow":-50043924.5698129386,"delta_flow":262.3032752531,"net_call_prem":-126906.0,"net_put_prem":-212146.0},{"strike":705.0,"call_prem_buy":241147.5,"call_prem_sell":230907.5,"put_prem_buy":467607.0,"put_prem_sell":470659.0,"gamma_flow":1682.0685118915,"charm_flow":16980560.8962693103,"delta_flow":-88.2376470214,"net_call_prem":10240.0,"net_put_prem":-3052.0},{"strike":704.0,"call_prem_buy":838.5,"call_prem_sell":838.5,"put_prem_buy":164789.0,"put_prem_sell":309650.0,"gamma_flow":-3581.9521170702,"charm_flow":-37070159.0055219308,"delta_flow":223.8920657866,"net_call_prem":0.0,"net_put_prem":-144861.0},{"strike":703.0,"call_prem_buy":4229.5,"call_prem_sell":17250.5,"put_prem_buy":188131.0,"put_prem_sell":166472.0,"gamma_flow":581.46013907,"charm_flow":3332748.2935282518,"delta_flow":-63.3878672903,"net_call_prem":-13021.0,"net_put_prem":21659.0},{"strike":702.0,"call_prem_buy":19151.0,"call_prem_sell":30750.0,"put_prem_buy":276017.0,"put_prem_sell":148291.0,"gamma_flow":3366.4338444447,"charm_flow":31677617.9821307994,"delta_flow":-243.3550236332,"net_call_prem":-11599.0,"net_put_prem":127726.0},{"strike":701.0,"call_prem_buy":80537.5,"call_prem_sell":13322.5,"put_prem_buy":105095.0,"put_prem_sell":166362.0,"gamma_flow":-683.4626027424,"charm_flow":-2888564.8196862163,"delta_flow":101.5868930134,"net_call_prem":67215.0,"net_put_prem":-61267.0},{"strike":700.0,"call_prem_buy":86644.0,"call_prem_sell":179505.0,"put_prem_buy":638339.0,"put_prem_sell":420221.0,"gamma_flow":5483.1712545561,"charm_flow":55538809.4970208704,"delta_flow":-464.0370205895,"net_call_prem":-92861.0,"net_put_prem":218118.0},{"strike":699.0,"call_prem_buy":9816.0,"call_prem_sell":0.0,"put_prem_buy":72664.0,"put_prem_sell":66609.0,"gamma_flow":722.0785485348,"charm_flow":12821936.5445328839,"delta_flow":-29.2113525401,"net_call_prem":9816.0,"net_put_prem":6055.0},{"strike":698.0,"call_prem_buy":5076.0,"call_prem_sell":91542.0,"put_prem_buy":91185.0,"put_prem_sell":41396.0,"gamma_flow":1542.791342797,"charm_flow":23252623.2218717411,"delta_flow":-131.8337477927,"net_call_prem":-86466.0,"net_put_prem":49789.0},{"strike":697.0,"call_prem_buy":2583.0,"call_prem_sell":0.0,"put_prem_buy":39502.0,"put_prem_sell":108524.0,"gamma_flow":-1798.8535906881,"charm_flow":-29086671.4164428227,"delta_flow":105.8031501853,"net_call_prem":2583.0,"net_put_prem":-69022.0},{"strike":696.0,"call_prem_buy":80826.0,"call_prem_sell":0.0,"put_prem_buy":42135.5,"put_prem_sell":33508.5,"gamma_flow":124.2484759289,"charm_flow":-507270.1913306246,"delta_flow":18.986654304,"net_call_prem":80826.0,"net_put_prem":8627.0},{"strike":695.0,"call_prem_buy":1108.5,"call_prem_sell":44068.5,"put_prem_buy":48654.0,"put_prem_sell":36800.0,"gamma_flow":473.3075730889,"charm_flow":7469819.3421944212,"delta_flow":-48.0667548276,"net_call_prem":-42960.0,"net_put_prem":11854.0},{"strike":694.0,"call_prem_buy":0.0,"call_prem_sell":21800.0,"put_prem_buy":109110.0,"put_prem_sell":39358.0,"gamma_flow":1789.2738244562,"charm_flow":27234471.7902393602,"delta_flow":-129.1239280668,"net_call_prem":-21800.0,"net_put_prem":69752.0},{"strike":693.0,"call_prem_buy":1201.0,"call_prem_sell":1201.0,"put_prem_buy":22085.0,"put_prem_sell":7673.0,"gamma_flow":438.7643487234,"charm_flow":7157518.8083295692,"delta_flow":-27.5322334843,"net_call_prem":0.0,"net_put_prem":14412.0},{"strike":692.0,"call_prem_buy":0.0,"call_prem_sell":0.0,"put_prem_buy":7235.0,"put_prem_sell":5610.0,"gamma_flow":70.5764045832,"charm_flow":1168666.7912250625,"delta_flow":-4.8456947711,"net_call_prem":0.0,"net_put_prem":1625.0}]