[{"strike":3180.0,"call_prem_buy":985950000.0,"call_prem_sell":0.0,"put_prem_buy":0.0,"put_prem_sell":979680000.0,"gamma_flow":6.382502516e-21,"charm_flow":-0.0,"delta_flow":3140.0,"net_call_prem":985950000.0,"net_put_prem":-979680000.0},{"strike":3050.0,"call_prem_buy":0.0,"call_prem_sell":0.0,"put_prem_buy":0.0,"put_prem_sell":12950.0,"gamma_flow":-0.0,"charm_flow":0.0000000021,"delta_flow":1.0,"net_call_prem":0.0,"net_put_prem":-12950.0},{"strike":3040.0,"call_prem_buy":0.0,"call_prem_sell":0.0,"put_prem_buy":11500.0,"put_prem_sell":0.0,"gamma_flow":0.0,"charm_flow":-0.0000002437,"delta_flow":-1.0,"net_call_prem":0.0,"net_put_prem":11500.0},{"strike":3030.0,"call_prem_buy":60.0,"call_prem_sell":0.0,"put_prem_buy":9850.0,"put_prem_sell":0.0,"gamma_flow":0.0000496446,"charm_flow":-3.7680157432,"delta_flow":-0.9999977836,"net_call_prem":60.0,"net_put_prem":9850.0},{"strike":3010.0,"call_prem_buy":450.0,"call_prem_sell":0.0,"put_prem_buy":0.0,"put_prem_sell":0.0,"gamma_flow":0.0002577811,"charm_flow":-15.9357348704,"delta_flow":0.0000098371,"net_call_prem":450.0,"net_put_prem":0.0},{"strike":3000.0,"call_prem_buy":260.0,"call_prem_sell":0.0,"put_prem_buy":0.0,"put_prem_sell":0.0,"gamma_flow":0.0010259552,"charm_flow":-56.165243823,"delta_flow":0.0000356923,"net_call_prem":260.0,"net_put_prem":0.0},{"strike":2990.0,"call_prem_buy":9500.0,"call_prem_sell":0.0,"put_prem_buy":0.0,"put_prem_sell":0.0,"gamma_flow":0.0067435409,"charm_flow":-321.3298542103,"delta_flow":0.0002342965,"net_call_prem":9500.0,"net_put_prem":0.0},{"strike":2980.0,"call_prem_buy":0.0,"call_prem_sell":110.0,"put_prem_buy":3500.0,"put_prem_sell":0.0,"gamma_flow":0.3152304129,"charm_flow":-12964.5474607602,"delta_flow":-0.9753814046,"net_call_prem":-110.0,"net_put_prem":3500.0},{"strike":2960.0,"call_prem_buy":0.0,"call_prem_sell":3160.0,"put_prem_buy":0.0,"put_prem_sell":5600.0,"gamma_flow":-3.1100776782,"charm_flow":65704.4268763707,"delta_flow":0.9188291677,"net_call_prem":-3160.0,"net_put_prem":-5600.0},{"strike":2950.0,"call_prem_buy":2860.0,"call_prem_sell":5890.0,"put_prem_buy":1760.0,"put_prem_sell":5540.0,"gamma_flow":-81.5625024079,"charm_flow":454452.6570850813,"delta_flow":0.7848808056,"net_call_prem":-3030.0,"net_put_prem":-3780.0},{"strike":2940.0,"call_prem_buy":22225.0,"call_prem_sell":37445.0,"put_prem_buy":20220.0,"put_prem_sell":8575.0,"gamma_flow":-110.6190180058,"charm_flow":1189984.0347968375,"delta_flow":-19.7923479909,"net_call_prem":-15220.0,"net_put_prem":11645.0},{"strike":2930.0,"call_prem_buy":30600.0,"call_prem_sell":25070.0,"put_prem_buy":580.0,"put_prem_sell":39210.0,"gamma_flow":-88.1438151061,"charm_flow":292688.5979666418,"delta_flow":23.194075933,"net_call_prem":5530.0,"net_put_prem":-38630.0},{"strike":2920.0,"call_prem_buy":0.0,"call_prem_sell":91840.0,"put_prem_buy":7.5,"put_prem_sell":53942.5,"gamma_flow":-609.3703019274,"charm_flow":-1639822.7388226343,"delta_flow":-55.5783576022,"net_call_prem":-91840.0,"net_put_prem":-53935.0},{"strike":2910.0,"call_prem_buy":246555.0,"call_prem_sell":0.0,"put_prem_buy":2087.5,"put_prem_sell":49462.5,"gamma_flow":8.0065090121,"charm_flow":76825.5175471619,"delta_flow":123.8827512568,"net_call_prem":246555.0,"net_put_prem":-47375.0},{"strike":2900.0,"call_prem_buy":0.0,"call_prem_sell":32200.0,"put_prem_buy":0.0,"put_prem_sell":31885.0,"gamma_flow":-53.0183053909,"charm_flow":-915887.0967989408,"delta_flow":-20.6418716269,"net_call_prem":-32200.0,"net_put_prem":-31885.0},{"strike":2890.0,"call_prem_buy":0.0,"call_prem_sell":3800.0,"put_prem_buy":0.0,"put_prem_sell":4060.0,"gamma_flow":-1.8128632381,"charm_flow":-44588.0915089293,"delta_flow":-1.9300100377,"net_call_prem":-3800.0,"net_put_prem":-4060.0},{"strike":2880.0,"call_prem_buy":0.0,"call_prem_sell":0.0,"put_prem_buy":0.0,"put_prem_sell":5320.0,"gamma_flow":-0.2647637121,"charm_flow":-8459.9457956158,"delta_flow":0.0094241556,"net_call_prem":0.0,"net_put_prem":-5320.0},{"strike":2870.0,"call_prem_buy":0.0,"call_prem_sell":5750.0,"put_prem_buy":0.0,"put_prem_sell":220.0,"gamma_flow":-0.0099258447,"charm_flow":-390.433342251,"delta_flow":-1.9996562459,"net_call_prem":-5750.0,"net_put_prem":-220.0},{"strike":2860.0,"call_prem_buy":40950.0,"call_prem_sell":0.0,"put_prem_buy":0.0,"put_prem_sell":420.0,"gamma_flow":0.1426348524,"charm_flow":6662.5056150848,"delta_flow":5.9900807381,"net_call_prem":40950.0,"net_put_prem":-420.0},{"strike":2850.0,"call_prem_buy":141000.0,"call_prem_sell":0.0,"put_prem_buy":0.0,"put_prem_sell":240.0,"gamma_flow":0.2462410989,"charm_flow":13329.7703869455,"delta_flow":14.981521301,"net_call_prem":141000.0,"net_put_prem":-240.0},{"strike":2840.0,"call_prem_buy":0.0,"call_prem_sell":0.0,"put_prem_buy":0.0,"put_prem_sell":750.0,"gamma_flow":-0.0013654521,"charm_flow":-84.1478749489,"delta_flow":0.0000577234,"net_call_prem":0.0,"net_put_prem":-750.0},{"strike":2830.0,"call_prem_buy":0.0,"call_prem_sell":0.0,"put_prem_buy":0.0,"put_prem_sell":180.0,"gamma_flow":-0.0001025275,"charm_flow":-7.0858507057,"delta_flow":0.0000042889,"net_call_prem":0.0,"net_put_prem":-180.0},{"strike":2820.0,"call_prem_buy":0.0,"call_prem_sell":0.0,"put_prem_buy":0.0,"put_prem_sell":100.0,"gamma_flow":-0.0002400926,"charm_flow":-18.3954416224,"delta_flow":0.0000108829,"net_call_prem":0.0,"net_put_prem":-100.0},{"strike":2810.0,"call_prem_buy":0.0,"call_prem_sell":0.0,"put_prem_buy":0.0,"put_prem_sell":125.0,"gamma_flow":-0.0000865505,"charm_flow":-7.2832525159,"delta_flow":0.0000042201,"net_call_prem":0.0,"net_put_prem":-125.0},{"strike":2800.0,"call_prem_buy":0.0,"call_prem_sell":0.0,"put_prem_buy":0.0,"put_prem_sell":260.0,"gamma_flow":-0.0000512714,"charm_flow":-4.7020269732,"delta_flow":0.000002674,"net_call_prem":0.0,"net_put_prem":-260.0},{"strike":2790.0,"call_prem_buy":27000.0,"call_prem_sell":0.0,"put_prem_buy":0.0,"put_prem_sell":2695.0,"gamma_flow":0.0054406895,"charm_flow":539.612367026,"delta_flow":1.9993767093,"net_call_prem":27000.0,"net_put_prem":-2695.0},{"strike":2780.0,"call_prem_buy":14500.0,"call_prem_sell":0.0,"put_prem_buy":0.0,"put_prem_sell":350.0,"gamma_flow":0.0023267233,"charm_flow":248.4614038954,"delta_flow":0.9997286513,"net_call_prem":14500.0,"net_put_prem":-350.0},{"strike":2770.0,"call_prem_buy":0.0,"call_prem_sell":0.0,"put_prem_buy":0.0,"put_prem_sell":320.0,"gamma_flow":-0.000093308,"charm_flow":-10.6876329707,"delta_flow":0.0000057959,"net_call_prem":0.0,"net_put_prem":-320.0},{"strike":2750.0,"call_prem_buy":0.0,"call_prem_sell":80000.0,"put_prem_buy":0.0,"put_prem_sell":840.0,"gamma_flow":-0.00030947,"charm_flow":-40.1931906733,"delta_flow":-9.9999762544,"net_call_prem":-80000.0,"net_put_prem":-840.0},{"strike":2730.0,"call_prem_buy":0.0,"call_prem_sell":0.0,"put_prem_buy":0.0,"put_prem_sell":600.0,"gamma_flow":-0.0000150761,"charm_flow":-2.1914823921,"delta_flow":0.0000011327,"net_call_prem":0.0,"net_put_prem":-600.0},{"strike":2720.0,"call_prem_buy":0.0,"call_prem_sell":0.0,"put_prem_buy":0.0,"put_prem_sell":5880.0,"gamma_flow":-0.0000581625,"charm_flow":-8.9067134384,"delta_flow":0.0000045546,"net_call_prem":0.0,"net_put_prem":-5880.0},{"strike":2710.0,"call_prem_buy":0.0,"call_prem_sell":0.0,"put_prem_buy":0.0,"put_prem_sell":3960.0,"gamma_flow":-0.0000417762,"charm_flow":-6.7233042251,"delta_flow":0.0000034049,"net_call_prem":0.0,"net_put_prem":-3960.0},{"strike":2700.0,"call_prem_buy":0.0,"call_prem_sell":0.0,"put_prem_buy":1105.0,"put_prem_sell":1105.0,"gamma_flow":0.0,"charm_flow":0.0,"delta_flow":0.0,"net_call_prem":0.0,"net_put_prem":0.0},{"strike":2670.0,"call_prem_buy":0.0,"call_prem_sell":0.0,"put_prem_buy":315.0,"put_prem_sell":315.0,"gamma_flow":0.0,"charm_flow":0.0,"delta_flow":0.0,"net_call_prem":0.0,"net_put_prem":0.0}]