[{"strike":768.0,"call_prem_buy":152.0,"call_prem_sell":0.0,"put_prem_buy":0.0,"put_prem_sell":0.0,"gamma_flow":10.9901947049,"charm_flow":-185117.9679977892,"delta_flow":0.2694318758,"net_call_prem":152.0,"net_put_prem":0.0},{"strike":767.0,"call_prem_buy":1.0,"call_prem_sell":1.0,"put_prem_buy":0.0,"put_prem_sell":2650.0,"gamma_flow":-0.8277911885,"charm_flow":13054.4203486238,"delta_flow":0.9389173099,"net_call_prem":0.0,"net_put_prem":-2650.0},{"strike":766.0,"call_prem_buy":1024.0,"call_prem_sell":24.0,"put_prem_buy":0.0,"put_prem_sell":0.0,"gamma_flow":80.9698129176,"charm_flow":-1226488.576910676,"delta_flow":2.3919666642,"net_call_prem":1000.0,"net_put_prem":0.0},{"strike":765.0,"call_prem_buy":105564108.0,"call_prem_sell":0.0,"put_prem_buy":9415.0,"put_prem_sell":115088391.0,"gamma_flow":5.7648020019,"charm_flow":-84478.9352411003,"delta_flow":1523.2151518436,"net_call_prem":105564108.0,"net_put_prem":-115078976.0},{"strike":764.0,"call_prem_buy":8.0,"call_prem_sell":0.0,"put_prem_buy":0.0,"put_prem_sell":0.0,"gamma_flow":0.2957903523,"charm_flow":-4407.4250451228,"delta_flow":0.007487161,"net_call_prem":8.0,"net_put_prem":0.0},{"strike":763.0,"call_prem_buy":998.0,"call_prem_sell":0.0,"put_prem_buy":1873.5,"put_prem_sell":4335.5,"gamma_flow":92.5341918589,"charm_flow":-1280835.0272765241,"delta_flow":3.0547944028,"net_call_prem":998.0,"net_put_prem":-2462.0},{"strike":762.0,"call_prem_buy":193.0,"call_prem_sell":300.0,"put_prem_buy":0.0,"put_prem_sell":0.0,"gamma_flow":-54.9197988336,"charm_flow":676647.6798968709,"delta_flow":-1.4110890506,"net_call_prem":-107.0,"net_put_prem":0.0},{"strike":761.0,"call_prem_buy":8607.0,"call_prem_sell":512.0,"put_prem_buy":0.0,"put_prem_sell":9592.0,"gamma_flow":640.7449741772,"charm_flow":-11296827.6473225895,"delta_flow":21.2984440709,"net_call_prem":8095.0,"net_put_prem":-9592.0},{"strike":760.0,"call_prem_buy":5520.0,"call_prem_sell":1126.0,"put_prem_buy":308653.0,"put_prem_sell":212515.0,"gamma_flow":176.0126363095,"charm_flow":-2459503.9729539957,"delta_flow":-38.0459684912,"net_call_prem":4394.0,"net_put_prem":96138.0},{"strike":759.0,"call_prem_buy":2421.5,"call_prem_sell":2465.5,"put_prem_buy":35200.0,"put_prem_sell":2225.0,"gamma_flow":-153.8758790922,"charm_flow":2905333.05373212,"delta_flow":-20.5615257931,"net_call_prem":-44.0,"net_put_prem":32975.0},{"strike":758.0,"call_prem_buy":8678.0,"call_prem_sell":997.0,"put_prem_buy":42508.0,"put_prem_sell":73597.0,"gamma_flow":770.4228964315,"charm_flow":-7942884.8863459704,"delta_flow":32.7627273925,"net_call_prem":7681.0,"net_put_prem":-31089.0},{"strike":757.0,"call_prem_buy":6616.5,"call_prem_sell":2799.5,"put_prem_buy":0.0,"put_prem_sell":41547.0,"gamma_flow":225.2684657384,"charm_flow":-1830157.8636937081,"delta_flow":25.4526212421,"net_call_prem":3817.0,"net_put_prem":-41547.0},{"strike":756.0,"call_prem_buy":11000.0,"call_prem_sell":10077.0,"put_prem_buy":16797.5,"put_prem_sell":16526.5,"gamma_flow":-666.0772816922,"charm_flow":5531656.6574510625,"delta_flow":-15.4201825306,"net_call_prem":923.0,"net_put_prem":271.0},{"strike":755.0,"call_prem_buy":26044.0,"call_prem_sell":9091.0,"put_prem_buy":535842.5,"put_prem_sell":29799.5,"gamma_flow":2296.3259074061,"charm_flow":-22082785.5172829032,"delta_flow":-224.3962947861,"net_call_prem":16953.0,"net_put_prem":506043.0},{"strike":754.0,"call_prem_buy":38284.0,"call_prem_sell":42383.0,"put_prem_buy":35434.0,"put_prem_sell":45347.0,"gamma_flow":-2127.6847511403,"charm_flow":21297164.3847516924,"delta_flow":-44.8785414294,"net_call_prem":-4099.0,"net_put_prem":-9913.0},{"strike":753.0,"call_prem_buy":39275.0,"call_prem_sell":49588.0,"put_prem_buy":23650.0,"put_prem_sell":53994.0,"gamma_flow":-1942.2799521565,"charm_flow":16631951.0765906852,"delta_flow":-39.9479583548,"net_call_prem":-10313.0,"net_put_prem":-30344.0},{"strike":752.0,"call_prem_buy":58890.5,"call_prem_sell":52535.5,"put_prem_buy":64419.5,"put_prem_sell":49482.5,"gamma_flow":579.0457029756,"charm_flow":-14220746.3712140843,"delta_flow":-8.4211713576,"net_call_prem":6355.0,"net_put_prem":14937.0},{"strike":751.0,"call_prem_buy":158588.0,"call_prem_sell":160395.0,"put_prem_buy":91264.5,"put_prem_sell":38950.5,"gamma_flow":-2676.9006323411,"charm_flow":21847646.4945394993,"delta_flow":-109.8419061168,"net_call_prem":-1807.0,"net_put_prem":52314.0},{"strike":750.0,"call_prem_buy":479809.5,"call_prem_sell":744971.5,"put_prem_buy":226276.5,"put_prem_sell":306704.5,"gamma_flow":-27713.5300565694,"charm_flow":141596420.4320810139,"delta_flow":-922.3568091802,"net_call_prem":-265162.0,"net_put_prem":-80428.0},{"strike":749.0,"call_prem_buy":401131.0,"call_prem_sell":812018.0,"put_prem_buy":477179.0,"put_prem_sell":307232.0,"gamma_flow":-36770.334769267,"charm_flow":152978481.139482379,"delta_flow":-1783.3686769367,"net_call_prem":-410887.0,"net_put_prem":169947.0},{"strike":748.0,"call_prem_buy":1597894.5,"call_prem_sell":1587817.5,"put_prem_buy":789277.0,"put_prem_sell":287981.0,"gamma_flow":-4269.4756449081,"charm_flow":-80553760.5011322051,"delta_flow":-1057.449322127,"net_call_prem":10077.0,"net_put_prem":501296.0},{"strike":747.0,"call_prem_buy":1658847.5,"call_prem_sell":2355710.5,"put_prem_buy":885503.0,"put_prem_sell":835326.0,"gamma_flow":-40494.4915303833,"charm_flow":83267919.6205362529,"delta_flow":-2358.8571530829,"net_call_prem":-696863.0,"net_put_prem":50177.0},{"strike":746.0,"call_prem_buy":4570310.5,"call_prem_sell":4615077.5,"put_prem_buy":1250013.0,"put_prem_sell":947982.0,"gamma_flow":-6946.5044300545,"charm_flow":150807892.1084815264,"delta_flow":-1187.7830368348,"net_call_prem":-44767.0,"net_put_prem":302031.0},{"strike":745.0,"call_prem_buy":8745591.0,"call_prem_sell":7966757.0,"put_prem_buy":5393254.0,"put_prem_sell":5069370.0,"gamma_flow":50834.2494082744,"charm_flow":-25047930.8322188258,"delta_flow":-1316.4016583449,"net_call_prem":778834.0,"net_put_prem":323884.0},{"strike":744.0,"call_prem_buy":9216267.0,"call_prem_sell":10313871.0,"put_prem_buy":8170375.5,"put_prem_sell":6174497.5,"gamma_flow":21895.3159369727,"charm_flow":177178811.5715483725,"delta_flow":-7511.7976601016,"net_call_prem":-1097604.0,"net_put_prem":1995878.0},{"strike":743.0,"call_prem_buy":10268907.5,"call_prem_sell":10094754.5,"put_prem_buy":7319704.5,"put_prem_sell":8241260.5,"gamma_flow":23579.6373432921,"charm_flow":-145877417.220190078,"delta_flow":1643.5383900131,"net_call_prem":174153.0,"net_put_prem":-921556.0},{"strike":742.0,"call_prem_buy":14848775.5,"call_prem_sell":11783759.5,"put_prem_buy":6319428.0,"put_prem_sell":9612109.0,"gamma_flow":12605.0630910701,"charm_flow":-249919801.5501095951,"delta_flow":11992.2446325829,"net_call_prem":3065016.0,"net_put_prem":-3292681.0},{"strike":741.0,"call_prem_buy":5346869.5,"call_prem_sell":8616978.5,"put_prem_buy":5972619.0,"put_prem_sell":7572280.0,"gamma_flow":-114934.6105299691,"charm_flow":-5866232.7668088665,"delta_flow":-3618.7419174771,"net_call_prem":-3270109.0,"net_put_prem":-1599661.0},{"strike":740.0,"call_prem_buy":7805888.0,"call_prem_sell":9540039.0,"put_prem_buy":9853198.0,"put_prem_sell":11353042.0,"gamma_flow":-54850.5974405074,"charm_flow":-27165381.6411252692,"delta_flow":-2155.3394950527,"net_call_prem":-1734151.0,"net_put_prem":-1499844.0},{"strike":739.0,"call_prem_buy":7455966.5,"call_prem_sell":8077420.5,"put_prem_buy":6556585.0,"put_prem_sell":7769471.0,"gamma_flow":-18374.3989238472,"charm_flow":38530006.1462171152,"delta_flow":466.659578886,"net_call_prem":-621454.0,"net_put_prem":-1212886.0},{"strike":738.0,"call_prem_buy":9538031.5,"call_prem_sell":9403001.5,"put_prem_buy":11990195.0,"put_prem_sell":8519544.0,"gamma_flow":56498.259982963,"charm_flow":103577480.7504300922,"delta_flow":-8095.6826266813,"net_call_prem":135030.0,"net_put_prem":3470651.0},{"strike":737.0,"call_prem_buy":6406035.0,"call_prem_sell":5898000.0,"put_prem_buy":11480829.0,"put_prem_sell":8098448.0,"gamma_flow":95668.9106665286,"charm_flow":-11486551.1683880724,"delta_flow":-4895.0443231827,"net_call_prem":508035.0,"net_put_prem":3382381.0},{"strike":736.0,"call_prem_buy":4507633.0,"call_prem_sell":3442346.0,"put_prem_buy":5829411.5,"put_prem_sell":7283100.5,"gamma_flow":-7958.7347040209,"charm_flow":-80458978.8391863853,"delta_flow":4537.8947465452,"net_call_prem":1065287.0,"net_put_prem":-1453689.0},{"strike":735.0,"call_prem_buy":1752128.5,"call_prem_sell":2068394.5,"put_prem_buy":7329448.5,"put_prem_sell":6442711.5,"gamma_flow":-1470.7239265711,"charm_flow":-35062786.7666112185,"delta_flow":-2213.7874752006,"net_call_prem":-316266.0,"net_put_prem":886737.0},{"strike":734.0,"call_prem_buy":871331.5,"call_prem_sell":958657.5,"put_prem_buy":2296460.0,"put_prem_sell":1844208.0,"gamma_flow":17697.5619052505,"charm_flow":73886042.7162200511,"delta_flow":-1498.8168157567,"net_call_prem":-87326.0,"net_put_prem":452252.0},{"strike":733.0,"call_prem_buy":954046.0,"call_prem_sell":947756.0,"put_prem_buy":1688605.5,"put_prem_sell":2219458.5,"gamma_flow":-17268.3479101169,"charm_flow":-49851146.954256773,"delta_flow":943.7181687977,"net_call_prem":6290.0,"net_put_prem":-530853.0},{"strike":732.0,"call_prem_buy":361073.5,"call_prem_sell":498813.5,"put_prem_buy":1485642.0,"put_prem_sell":1819017.0,"gamma_flow":-8357.4230201737,"charm_flow":-83824533.3940661699,"delta_flow":146.6443467877,"net_call_prem":-137740.0,"net_put_prem":-333375.0},{"strike":731.0,"call_prem_buy":483452.0,"call_prem_sell":485567.0,"put_prem_buy":890174.0,"put_prem_sell":1216072.0,"gamma_flow":-12031.7197985605,"charm_flow":-66202667.904847376,"delta_flow":476.4335740908,"net_call_prem":-2115.0,"net_put_prem":-325898.0},{"strike":730.0,"call_prem_buy":613857.5,"call_prem_sell":730392.5,"put_prem_buy":1155297.0,"put_prem_sell":1383837.0,"gamma_flow":-1912.6042534393,"charm_flow":-22873044.8377488144,"delta_flow":17.703378612,"net_call_prem":-116535.0,"net_put_prem":-228540.0},{"strike":729.0,"call_prem_buy":152669.5,"call_prem_sell":301325.5,"put_prem_buy":321098.0,"put_prem_sell":527131.0,"gamma_flow":-7371.3526747003,"charm_flow":-53284455.4313733652,"delta_flow":217.5641634527,"net_call_prem":-148656.0,"net_put_prem":-206033.0},{"strike":728.0,"call_prem_buy":286916.0,"call_prem_sell":470664.0,"put_prem_buy":392850.5,"put_prem_sell":437656.5,"gamma_flow":-847.9549184111,"charm_flow":1321604.4667740874,"delta_flow":-97.627147101,"net_call_prem":-183748.0,"net_put_prem":-44806.0},{"strike":727.0,"call_prem_buy":201295.0,"call_prem_sell":253622.0,"put_prem_buy":306830.0,"put_prem_sell":189889.0,"gamma_flow":5075.2263034136,"charm_flow":46234502.4869608432,"delta_flow":-318.354803297,"net_call_prem":-52327.0,"net_put_prem":116941.0},{"strike":726.0,"call_prem_buy":521497.0,"call_prem_sell":256690.0,"put_prem_buy":263940.5,"put_prem_sell":192986.5,"gamma_flow":3840.665445154,"charm_flow":35553660.1972263828,"delta_flow":-11.1489658577,"net_call_prem":264807.0,"net_put_prem":70954.0},{"strike":725.0,"call_prem_buy":238117.0,"call_prem_sell":170476.0,"put_prem_buy":217960.0,"put_prem_sell":189580.0,"gamma_flow":2192.9639991382,"charm_flow":27798395.1676570661,"delta_flow":-71.6984603852,"net_call_prem":67641.0,"net_put_prem":28380.0},{"strike":724.0,"call_prem_buy":106378.0,"call_prem_sell":77221.0,"put_prem_buy":136508.0,"put_prem_sell":182387.0,"gamma_flow":-2045.8088581194,"charm_flow":-26696549.9594108015,"delta_flow":101.1523507097,"net_call_prem":29157.0,"net_put_prem":-45879.0},{"strike":723.0,"call_prem_buy":108730.0,"call_prem_sell":114506.0,"put_prem_buy":77751.0,"put_prem_sell":70066.0,"gamma_flow":635.7080141575,"charm_flow":6189945.6270963205,"delta_flow":-40.4470056103,"net_call_prem":-5776.0,"net_put_prem":7685.0},{"strike":722.0,"call_prem_buy":132484.0,"call_prem_sell":136491.0,"put_prem_buy":60773.0,"put_prem_sell":39159.0,"gamma_flow":773.8088432402,"charm_flow":11071533.1103936359,"delta_flow":-45.0909533339,"net_call_prem":-4007.0,"net_put_prem":21614.0},{"strike":721.0,"call_prem_buy":147106.0,"call_prem_sell":70536.0,"put_prem_buy":62949.0,"put_prem_sell":33379.0,"gamma_flow":1241.5788001042,"charm_flow":16649092.7547631152,"delta_flow":-31.0059497,"net_call_prem":76570.0,"net_put_prem":29570.0},{"strike":720.0,"call_prem_buy":181315.0,"call_prem_sell":135584.0,"put_prem_buy":70043.0,"put_prem_sell":63427.0,"gamma_flow":695.638866684,"charm_flow":10976876.0445845332,"delta_flow":-11.2231704682,"net_call_prem":45731.0,"net_put_prem":6616.0},{"strike":719.0,"call_prem_buy":54668.0,"call_prem_sell":3974.0,"put_prem_buy":37857.0,"put_prem_sell":18164.0,"gamma_flow":1165.8827247447,"charm_flow":20267462.2868336476,"delta_flow":-24.6861832479,"net_call_prem":50694.0,"net_put_prem":19693.0},{"strike":718.0,"call_prem_buy":5328.0,"call_prem_sell":8168.0,"put_prem_buy":33242.0,"put_prem_sell":17018.0,"gamma_flow":794.2717653005,"charm_flow":13533975.4353155233,"delta_flow":-42.3385163868,"net_call_prem":-2840.0,"net_put_prem":16224.0},{"strike":717.0,"call_prem_buy":4052.0,"call_prem_sell":14224.0,"put_prem_buy":37025.0,"put_prem_sell":7612.0,"gamma_flow":1581.2610141096,"charm_flow":30056705.1804769747,"delta_flow":-77.7658357203,"net_call_prem":-10172.0,"net_put_prem":29413.0},{"strike":716.0,"call_prem_buy":34224.0,"call_prem_sell":34320.0,"put_prem_buy":24088.0,"put_prem_sell":18918.0,"gamma_flow":303.5619989995,"charm_flow":5466488.9568212805,"delta_flow":-18.0429501379,"net_call_prem":-96.0,"net_put_prem":5170.0},{"strike":715.0,"call_prem_buy":332797.0,"call_prem_sell":224590.0,"put_prem_buy":28109.0,"put_prem_sell":4712.0,"gamma_flow":1259.9755514422,"charm_flow":24410478.761113923,"delta_flow":-21.1805231174,"net_call_prem":108207.0,"net_put_prem":23397.0},{"strike":714.0,"call_prem_buy":204692.0,"call_prem_sell":0.0,"put_prem_buy":17960.0,"put_prem_sell":4246.0,"gamma_flow":578.6152358008,"charm_flow":10934385.6446482521,"delta_flow":42.8269752792,"net_call_prem":204692.0,"net_put_prem":13714.0},{"strike":713.0,"call_prem_buy":89756.0,"call_prem_sell":0.0,"put_prem_buy":12.0,"put_prem_sell":20812.0,"gamma_flow":-842.9423569013,"charm_flow":-17734134.4391987994,"delta_flow":75.0435039733,"net_call_prem":89756.0,"net_put_prem":-20800.0}]